uw/__init__.py
uw/bots.h
uw/commands.py
uw/game.py
uw/helpers.py
uw/map.py
uw/prototypes.py
uw/world.py
unnatural_worlds_api-21.7.1.dist-info/METADATA
unnatural_worlds_api-21.7.1.dist-info/WHEEL
unnatural_worlds_api-21.7.1.dist-info/top_level.txt
unnatural_worlds_api-21.7.1.dist-info/RECORD
