Metadata-Version: 2.1
Name: unnatural-worlds-api
Version: 21.7.1
Summary: Unnatural Worlds Bot API
Home-page: 
Author: tivvit
Author-email: tivvitmail@gmail.com
Keywords: uw,unnatural worlds
